{
	"kind": "Pod",
	"apiVersion": "v1",
	"metadata": {
		"name": "pod-370237482-0",
		"namespace": "default",
		"creationTimestamp": null,
		"annotations": {
			"simSpec": "\n- seconds: 5\n  resourceUsage:\n    cpu: 3073m\n    memory: 6088Mi\n    nvidia.com/gpu: 0\n\n- seconds: 5\n  resourceUsage:\n    cpu: 2949m\n    memory: 6088Mi\n    nvidia.com/gpu: 0\n\n- seconds: 5\n  resourceUsage:\n    cpu: 3073m\n    memory: 6072Mi\n    nvidia.com/gpu: 0\n\n- seconds: 5\n  resourceUsage:\n    cpu: 2941m\n    memory: 6088Mi\n    nvidia.com/gpu: 0\n\n- seconds: 5\n  resourceUsage:\n    cpu: 3086m\n    memory: 6088Mi\n    nvidia.com/gpu: 0\n\n- seconds: 5\n  resourceUsage:\n    cpu: 2988m\n    memory: 6072Mi\n    nvidia.com/gpu: 0\n\n- seconds: 5\n  resourceUsage:\n    cpu: 3113m\n    memory: 6096Mi\n    nvidia.com/gpu: 0\n\n- seconds: 5\n  resourceUsage:\n    cpu: 2968m\n    memory: 6072Mi\n    nvidia.com/gpu: 0\n\n- seconds: 5\n  resourceUsage:\n    cpu: 3156m\n    memory: 6088Mi\n    nvidia.com/gpu: 0\n\n- seconds: 5\n  resourceUsage:\n    cpu: 2965m\n    memory: 6080Mi\n    nvidia.com/gpu: 0\n\n- seconds: 5\n  resourceUsage:\n    cpu: 3136m\n    memory: 6096Mi\n    nvidia.com/gpu: 0\n\n- seconds: 5\n  resourceUsage:\n    cpu: 2972m\n    memory: 6055Mi\n    nvidia.com/gpu: 0\n\n- seconds: 5\n  resourceUsage:\n    cpu: 3164m\n    memory: 6111Mi\n    nvidia.com/gpu: 0\n\n- seconds: 5\n  resourceUsage:\n    cpu: 2949m\n    memory: 6063Mi\n    nvidia.com/gpu: 0\n\n- seconds: 5\n  resourceUsage:\n    cpu: 3140m\n    memory: 6088Mi\n    nvidia.com/gpu: 0\n\n- seconds: 5\n  resourceUsage:\n    cpu: 3004m\n    memory: 6072Mi\n    nvidia.com/gpu: 0\n\n- seconds: 5\n  resourceUsage:\n    cpu: 3125m\n    memory: 6119Mi\n    nvidia.com/gpu: 0\n\n- seconds: 5\n  resourceUsage:\n    cpu: 3004m\n    memory: 6063Mi\n    nvidia.com/gpu: 0\n\n- seconds: 5\n  resourceUsage:\n    cpu: 3152m\n    memory: 6119Mi\n    nvidia.com/gpu: 0\n\n- seconds: 5\n  resourceUsage:\n    cpu: 2952m\n    memory: 6055Mi\n    nvidia.com/gpu: 0\n\n- seconds: 5\n  resourceUsage:\n    cpu: 3140m\n    memory: 6096Mi\n    nvidia.com/gpu: 0\n\n- seconds: 5\n  resourceUsage:\n    cpu: 3023m\n    memory: 6072Mi\n    nvidia.com/gpu: 0\n\n- seconds: 5\n  resourceUsage:\n    cpu: 3168m\n    memory: 6104Mi\n    nvidia.com/gpu: 0\n\n- seconds: 5\n  resourceUsage:\n    cpu: 3034m\n    memory: 6072Mi\n    nvidia.com/gpu: 0\n\n- seconds: 5\n  resourceUsage:\n    cpu: 3125m\n    memory: 6127Mi\n    nvidia.com/gpu: 0\n\n- seconds: 5\n  resourceUsage:\n    cpu: 3023m\n    memory: 6080Mi\n    nvidia.com/gpu: 0\n\n- seconds: 5\n  resourceUsage:\n    cpu: 3148m\n    memory: 6111Mi\n    nvidia.com/gpu: 0\n\n- seconds: 5\n  resourceUsage:\n    cpu: 3234m\n    memory: 6072Mi\n    nvidia.com/gpu: 0\n\n- seconds: 5\n  resourceUsage:\n    cpu: 2933m\n    memory: 6119Mi\n    nvidia.com/gpu: 0\n\n- seconds: 5\n  resourceUsage:\n    cpu: 3324m\n    memory: 6088Mi\n    nvidia.com/gpu: 0\n\n- seconds: 5\n  resourceUsage:\n    cpu: 2792m\n    memory: 6096Mi\n    nvidia.com/gpu: 0\n\n- seconds: 5\n  resourceUsage:\n    cpu: 3320m\n    memory: 6111Mi\n    nvidia.com/gpu: 0\n\n- seconds: 5\n  resourceUsage:\n    cpu: 2929m\n    memory: 6088Mi\n    nvidia.com/gpu: 0\n\n- seconds: 5\n  resourceUsage:\n    cpu: 3199m\n    memory: 6096Mi\n    nvidia.com/gpu: 0\n\n- seconds: 5\n  resourceUsage:\n    cpu: 2984m\n    memory: 6088Mi\n    nvidia.com/gpu: 0\n\n- seconds: 5\n  resourceUsage:\n    cpu: 3257m\n    memory: 6104Mi\n    nvidia.com/gpu: 0\n\n- seconds: 5\n  resourceUsage:\n    cpu: 2898m\n    memory: 6063Mi\n    nvidia.com/gpu: 0\n\n- seconds: 5\n  resourceUsage:\n    cpu: 3175m\n    memory: 6127Mi\n    nvidia.com/gpu: 0\n\n- seconds: 5\n  resourceUsage:\n    cpu: 2926m\n    memory: 6080Mi\n    nvidia.com/gpu: 0\n\n- seconds: 5\n  resourceUsage:\n    cpu: 3199m\n    memory: 6111Mi\n    nvidia.com/gpu: 0\n\n- seconds: 5\n  resourceUsage:\n    cpu: 3011m\n    memory: 6088Mi\n    nvidia.com/gpu: 0\n\n- seconds: 5\n  resourceUsage:\n    cpu: 3218m\n    memory: 6111Mi\n    nvidia.com/gpu: 0\n\n- seconds: 5\n  resourceUsage:\n    cpu: 2972m\n    memory: 6072Mi\n    nvidia.com/gpu: 0\n\n- seconds: 5\n  resourceUsage:\n    cpu: 3261m\n    memory: 6127Mi\n    nvidia.com/gpu: 0\n\n- seconds: 5\n  resourceUsage:\n    cpu: 2972m\n    memory: 6072Mi\n    nvidia.com/gpu: 0\n\n- seconds: 5\n  resourceUsage:\n    cpu: 3191m\n    memory: 6111Mi\n    nvidia.com/gpu: 0\n\n- seconds: 5\n  resourceUsage:\n    cpu: 3249m\n    memory: 6063Mi\n    nvidia.com/gpu: 0\n\n- seconds: 5\n  resourceUsage:\n    cpu: 3062m\n    memory: 6127Mi\n    nvidia.com/gpu: 0\n\n- seconds: 5\n  resourceUsage:\n    cpu: 3383m\n    memory: 6088Mi\n    nvidia.com/gpu: 0\n\n- seconds: 5\n  resourceUsage:\n    cpu: 2968m\n    memory: 6088Mi\n    nvidia.com/gpu: 0\n\n- seconds: 5\n  resourceUsage:\n    cpu: 3203m\n    memory: 6111Mi\n    nvidia.com/gpu: 0\n\n- seconds: 5\n  resourceUsage:\n    cpu: 2929m\n    memory: 6080Mi\n    nvidia.com/gpu: 0\n\n- seconds: 5\n  resourceUsage:\n    cpu: 3261m\n    memory: 6104Mi\n    nvidia.com/gpu: 0\n\n- seconds: 5\n  resourceUsage:\n    cpu: 3070m\n    memory: 6096Mi\n    nvidia.com/gpu: 0\n\n- seconds: 5\n  resourceUsage:\n    cpu: 3136m\n    memory: 6111Mi\n    nvidia.com/gpu: 0\n\n- seconds: 5\n  resourceUsage:\n    cpu: 3015m\n    memory: 6072Mi\n    nvidia.com/gpu: 0\n\n- seconds: 5\n  resourceUsage:\n    cpu: 3152m\n    memory: 6127Mi\n    nvidia.com/gpu: 0\n\n- seconds: 5\n  resourceUsage:\n    cpu: 2968m\n    memory: 6080Mi\n    nvidia.com/gpu: 0\n\n- seconds: 5\n  resourceUsage:\n    cpu: 3125m\n    memory: 6111Mi\n    nvidia.com/gpu: 0\n\n- seconds: 5\n  resourceUsage:\n    cpu: 3000m\n    memory: 6096Mi\n    nvidia.com/gpu: 0\n\n- seconds: 5\n  resourceUsage:\n    cpu: 3086m\n    memory: 6104Mi\n    nvidia.com/gpu: 0\n\n- seconds: 5\n  resourceUsage:\n    cpu: 2968m\n    memory: 6063Mi\n    nvidia.com/gpu: 0\n\n- seconds: 5\n  resourceUsage:\n    cpu: 3222m\n    memory: 6127Mi\n    nvidia.com/gpu: 0\n\n- seconds: 5\n  resourceUsage:\n    cpu: 3062m\n    memory: 6072Mi\n    nvidia.com/gpu: 0\n\n- seconds: 5\n  resourceUsage:\n    cpu: 3242m\n    memory: 6119Mi\n    nvidia.com/gpu: 0\n\n- seconds: 5\n  resourceUsage:\n    cpu: 3128m\n    memory: 6088Mi\n    nvidia.com/gpu: 0\n\n- seconds: 5\n  resourceUsage:\n    cpu: 3179m\n    memory: 6135Mi\n    nvidia.com/gpu: 0\n\n- seconds: 5\n  resourceUsage:\n    cpu: 3292m\n    memory: 6104Mi\n    nvidia.com/gpu: 0\n\n- seconds: 5\n  resourceUsage:\n    cpu: 2956m\n    memory: 6119Mi\n    nvidia.com/gpu: 0\n\n- seconds: 5\n  resourceUsage:\n    cpu: 3448m\n    memory: 6088Mi\n    nvidia.com/gpu: 0\n\n- seconds: 5\n  resourceUsage:\n    cpu: 2672m\n    memory: 6111Mi\n    nvidia.com/gpu: 0\n\n- seconds: 5\n  resourceUsage:\n    cpu: 3406m\n    memory: 6111Mi\n    nvidia.com/gpu: 0\n\n- seconds: 5\n  resourceUsage:\n    cpu: 2519m\n    memory: 6111Mi\n    nvidia.com/gpu: 0\n\n- seconds: 5\n  resourceUsage:\n    cpu: 3390m\n    memory: 6104Mi\n    nvidia.com/gpu: 0\n\n- seconds: 5\n  resourceUsage:\n    cpu: 2796m\n    memory: 6111Mi\n    nvidia.com/gpu: 0\n\n- seconds: 5\n  resourceUsage:\n    cpu: 3023m\n    memory: 6096Mi\n    nvidia.com/gpu: 0\n\n- seconds: 5\n  resourceUsage:\n    cpu: 2769m\n    memory: 6080Mi\n    nvidia.com/gpu: 0\n\n- seconds: 5\n  resourceUsage:\n    cpu: 3125m\n    memory: 6119Mi\n    nvidia.com/gpu: 0\n\n- seconds: 5\n  resourceUsage:\n    cpu: 2789m\n    memory: 6096Mi\n    nvidia.com/gpu: 0\n\n- seconds: 5\n  resourceUsage:\n    cpu: 3039m\n    memory: 6135Mi\n    nvidia.com/gpu: 0\n\n- seconds: 5\n  resourceUsage:\n    cpu: 2714m\n    memory: 6096Mi\n    nvidia.com/gpu: 0\n\n- seconds: 5\n  resourceUsage:\n    cpu: 3034m\n    memory: 6111Mi\n    nvidia.com/gpu: 0\n\n- seconds: 5\n  resourceUsage:\n    cpu: 2792m\n    memory: 6096Mi\n    nvidia.com/gpu: 0\n\n- seconds: 5\n  resourceUsage:\n    cpu: 3015m\n    memory: 6111Mi\n    nvidia.com/gpu: 0\n\n- seconds: 5\n  resourceUsage:\n    cpu: 2792m\n    memory: 6080Mi\n    nvidia.com/gpu: 0\n\n- seconds: 5\n  resourceUsage:\n    cpu: 3027m\n    memory: 6135Mi\n    nvidia.com/gpu: 0\n\n- seconds: 5\n  resourceUsage:\n    cpu: 2832m\n    memory: 6088Mi\n    nvidia.com/gpu: 0\n\n- seconds: 5\n  resourceUsage:\n    cpu: 3089m\n    memory: 6127Mi\n    nvidia.com/gpu: 0\n\n- seconds: 5\n  resourceUsage:\n    cpu: 2863m\n    memory: 6096Mi\n    nvidia.com/gpu: 0\n\n- seconds: 5\n  resourceUsage:\n    cpu: 3031m\n    memory: 6127Mi\n    nvidia.com/gpu: 0\n\n- seconds: 5\n  resourceUsage:\n    cpu: 2777m\n    memory: 6080Mi\n    nvidia.com/gpu: 0\n\n- seconds: 5\n  resourceUsage:\n    cpu: 3027m\n    memory: 6144Mi\n    nvidia.com/gpu: 0\n\n- seconds: 5\n  resourceUsage:\n    cpu: 2695m\n    memory: 6088Mi\n    nvidia.com/gpu: 0\n\n- seconds: 5\n  resourceUsage:\n    cpu: 2960m\n    memory: 6127Mi\n    nvidia.com/gpu: 0\n\n- seconds: 5\n  resourceUsage:\n    cpu: 2926m\n    memory: 6096Mi\n    nvidia.com/gpu: 0\n\n- seconds: 5\n  resourceUsage:\n    cpu: 3089m\n    memory: 6144Mi\n    nvidia.com/gpu: 0\n\n- seconds: 5\n  resourceUsage:\n    cpu: 2828m\n    memory: 6104Mi\n    nvidia.com/gpu: 0\n\n- seconds: 5\n  resourceUsage:\n    cpu: 3589m\n    memory: 6160Mi\n    nvidia.com/gpu: 0\n\n- seconds: 5\n  resourceUsage:\n    cpu: 2937m\n    memory: 6080Mi\n    nvidia.com/gpu: 0\n\n- seconds: 5\n  resourceUsage:\n    cpu: 3093m\n    memory: 6135Mi\n    nvidia.com/gpu: 0\n\n- seconds: 5\n  resourceUsage:\n    cpu: 2808m\n    memory: 6088Mi\n    nvidia.com/gpu: 0\n\n- seconds: 5\n  resourceUsage:\n    cpu: 3023m\n    memory: 6119Mi\n    nvidia.com/gpu: 0\n\n- seconds: 5\n  resourceUsage:\n    cpu: 2839m\n    memory: 6104Mi\n    nvidia.com/gpu: 0\n\n- seconds: 5\n  resourceUsage:\n    cpu: 3125m\n    memory: 6135Mi\n    nvidia.com/gpu: 0\n\n- seconds: 5\n  resourceUsage:\n    cpu: 2851m\n    memory: 6096Mi\n    nvidia.com/gpu: 0\n\n- seconds: 5\n  resourceUsage:\n    cpu: 3132m\n    memory: 6144Mi\n    nvidia.com/gpu: 0\n\n- seconds: 5\n  resourceUsage:\n    cpu: 2613m\n    memory: 6088Mi\n    nvidia.com/gpu: 0\n\n- seconds: 5\n  resourceUsage:\n    cpu: 3425m\n    memory: 6135Mi\n    nvidia.com/gpu: 0\n\n- seconds: 5\n  resourceUsage:\n    cpu: 2882m\n    memory: 6104Mi\n    nvidia.com/gpu: 0\n\n- seconds: 5\n  resourceUsage:\n    cpu: 2960m\n    memory: 6127Mi\n    nvidia.com/gpu: 0\n\n- seconds: 5\n  resourceUsage:\n    cpu: 2832m\n    memory: 6096Mi\n    nvidia.com/gpu: 0\n\n- seconds: 5\n  resourceUsage:\n    cpu: 3058m\n    memory: 6127Mi\n    nvidia.com/gpu: 0\n\n- seconds: 5\n  resourceUsage:\n    cpu: 2851m\n    memory: 6096Mi\n    nvidia.com/gpu: 0\n\n- seconds: 5\n  resourceUsage:\n    cpu: 3128m\n    memory: 6111Mi\n    nvidia.com/gpu: 0\n\n- seconds: 5\n  resourceUsage:\n    cpu: 2882m\n    memory: 6119Mi\n    nvidia.com/gpu: 0\n\n- seconds: 5\n  resourceUsage:\n    cpu: 3027m\n    memory: 6119Mi\n    nvidia.com/gpu: 0\n\n- seconds: 5\n  resourceUsage:\n    cpu: 2484m\n    memory: 6104Mi\n    nvidia.com/gpu: 0\n\n- seconds: 5\n  resourceUsage:\n    cpu: 3425m\n    memory: 6135Mi\n    nvidia.com/gpu: 0\n\n- seconds: 5\n  resourceUsage:\n    cpu: 2562m\n    memory: 6119Mi\n    nvidia.com/gpu: 0\n\n- seconds: 5\n  resourceUsage:\n    cpu: 3328m\n    memory: 6104Mi\n    nvidia.com/gpu: 0\n\n- seconds: 5\n  resourceUsage:\n    cpu: 2746m\n    memory: 6127Mi\n    nvidia.com/gpu: 0\n\n- seconds: 5\n  resourceUsage:\n    cpu: 2917m\n    memory: 6096Mi\n    nvidia.com/gpu: 0\n\n- seconds: 5\n  resourceUsage:\n    cpu: 2988m\n    memory: 6135Mi\n    nvidia.com/gpu: 0\n\n- seconds: 5\n  resourceUsage:\n    cpu: 3023m\n    memory: 6096Mi\n    nvidia.com/gpu: 0\n\n- seconds: 5\n  resourceUsage:\n    cpu: 3132m\n    memory: 6135Mi\n    nvidia.com/gpu: 0\n\n- seconds: 5\n  resourceUsage:\n    cpu: 3027m\n    memory: 6104Mi\n    nvidia.com/gpu: 0\n\n- seconds: 5\n  resourceUsage:\n    cpu: 3144m\n    memory: 6152Mi\n    nvidia.com/gpu: 0\n\n- seconds: 5\n  resourceUsage:\n    cpu: 3027m\n    memory: 6088Mi\n    nvidia.com/gpu: 0\n\n- seconds: 5\n  resourceUsage:\n    cpu: 3136m\n    memory: 6144Mi\n    nvidia.com/gpu: 0\n\n- seconds: 5\n  resourceUsage:\n    cpu: 2995m\n    memory: 6104Mi\n    nvidia.com/gpu: 0\n\n- seconds: 5\n  resourceUsage:\n    cpu: 3160m\n    memory: 6135Mi\n    nvidia.com/gpu: 0\n\n- seconds: 5\n  resourceUsage:\n    cpu: 3050m\n    memory: 6088Mi\n    nvidia.com/gpu: 0\n\n- seconds: 5\n  resourceUsage:\n    cpu: 3195m\n    memory: 6144Mi\n    nvidia.com/gpu: 0\n\n- seconds: 5\n  resourceUsage:\n    cpu: 2992m\n    memory: 6111Mi\n    nvidia.com/gpu: 0\n\n- seconds: 5\n  resourceUsage:\n    cpu: 3164m\n    memory: 6127Mi\n    nvidia.com/gpu: 0\n\n- seconds: 5\n  resourceUsage:\n    cpu: 3000m\n    memory: 6119Mi\n    nvidia.com/gpu: 0\n\n- seconds: 5\n  resourceUsage:\n    cpu: 3187m\n    memory: 6119Mi\n    nvidia.com/gpu: 0\n\n- seconds: 5\n  resourceUsage:\n    cpu: 2672m\n    memory: 6127Mi\n    nvidia.com/gpu: 0\n\n- seconds: 5\n  resourceUsage:\n    cpu: 3070m\n    memory: 6104Mi\n    nvidia.com/gpu: 0\n\n- seconds: 5\n  resourceUsage:\n    cpu: 2965m\n    memory: 6127Mi\n    nvidia.com/gpu: 0\n\n- seconds: 5\n  resourceUsage:\n    cpu: 2921m\n    memory: 6088Mi\n    nvidia.com/gpu: 0\n\n- seconds: 5\n  resourceUsage:\n    cpu: 3171m\n    memory: 6144Mi\n    nvidia.com/gpu: 0\n\n- seconds: 5\n  resourceUsage:\n    cpu: 2921m\n    memory: 6096Mi\n    nvidia.com/gpu: 0\n\n- seconds: 5\n  resourceUsage:\n    cpu: 3183m\n    memory: 6160Mi\n    nvidia.com/gpu: 0\n\n- seconds: 5\n  resourceUsage:\n    cpu: 2956m\n    memory: 6096Mi\n    nvidia.com/gpu: 0\n\n- seconds: 5\n  resourceUsage:\n    cpu: 3175m\n    memory: 6127Mi\n    nvidia.com/gpu: 0\n\n- seconds: 5\n  resourceUsage:\n    cpu: 2952m\n    memory: 6088Mi\n    nvidia.com/gpu: 0\n\n- seconds: 5\n  resourceUsage:\n    cpu: 3249m\n    memory: 6144Mi\n    nvidia.com/gpu: 0\n\n- seconds: 5\n  resourceUsage:\n    cpu: 2898m\n    memory: 6104Mi\n    nvidia.com/gpu: 0\n\n- seconds: 5\n  resourceUsage:\n    cpu: 3082m\n    memory: 6119Mi\n    nvidia.com/gpu: 0\n\n- seconds: 5\n  resourceUsage:\n    cpu: 2886m\n    memory: 6111Mi\n    nvidia.com/gpu: 0\n\n- seconds: 5\n  resourceUsage:\n    cpu: 3168m\n    memory: 6119Mi\n    nvidia.com/gpu: 0\n\n- seconds: 5\n  resourceUsage:\n    cpu: 2691m\n    memory: 6111Mi\n    nvidia.com/gpu: 0\n\n- seconds: 5\n  resourceUsage:\n    cpu: 3136m\n    memory: 6111Mi\n    nvidia.com/gpu: 0\n\n- seconds: 5\n  resourceUsage:\n    cpu: 2746m\n    memory: 6152Mi\n    nvidia.com/gpu: 0\n\n- seconds: 5\n  resourceUsage:\n    cpu: 2941m\n    memory: 6104Mi\n    nvidia.com/gpu: 0\n\n- seconds: 5\n  resourceUsage:\n    cpu: 3113m\n    memory: 6160Mi\n    nvidia.com/gpu: 0\n\n- seconds: 5\n  resourceUsage:\n    cpu: 2941m\n    memory: 6111Mi\n    nvidia.com/gpu: 0\n\n- seconds: 5\n  resourceUsage:\n    cpu: 3136m\n    memory: 6152Mi\n    nvidia.com/gpu: 0\n\n- seconds: 5\n  resourceUsage:\n    cpu: 3019m\n    memory: 6119Mi\n    nvidia.com/gpu: 0\n\n- seconds: 5\n  resourceUsage:\n    cpu: 3175m\n    memory: 6160Mi\n    nvidia.com/gpu: 0\n\n- seconds: 5\n  resourceUsage:\n    cpu: 3034m\n    memory: 6111Mi\n    nvidia.com/gpu: 0\n\n- seconds: 5\n  resourceUsage:\n    cpu: 3183m\n    memory: 6152Mi\n    nvidia.com/gpu: 0\n\n- seconds: 5\n  resourceUsage:\n    cpu: 3073m\n    memory: 6127Mi\n    nvidia.com/gpu: 0\n\n- seconds: 5\n  resourceUsage:\n    cpu: 3218m\n    memory: 6168Mi\n    nvidia.com/gpu: 0\n\n- seconds: 5\n  resourceUsage:\n    cpu: 3082m\n    memory: 6111Mi\n    nvidia.com/gpu: 0\n\n- seconds: 5\n  resourceUsage:\n    cpu: 3230m\n    memory: 6160Mi\n    nvidia.com/gpu: 0\n\n- seconds: 5\n  resourceUsage:\n    cpu: 3062m\n    memory: 6119Mi\n    nvidia.com/gpu: 0\n\n- seconds: 5\n  resourceUsage:\n    cpu: 3226m\n    memory: 6160Mi\n    nvidia.com/gpu: 0\n\n- seconds: 5\n  resourceUsage:\n    cpu: 3136m\n    memory: 6135Mi\n    nvidia.com/gpu: 0\n\n- seconds: 5\n  resourceUsage:\n    cpu: 3234m\n    memory: 6168Mi\n    nvidia.com/gpu: 0\n\n- seconds: 5\n  resourceUsage:\n    cpu: 3191m\n    memory: 6127Mi\n    nvidia.com/gpu: 0\n\n- seconds: 5\n  resourceUsage:\n    cpu: 3292m\n    memory: 6176Mi\n    nvidia.com/gpu: 0\n\n- seconds: 5\n  resourceUsage:\n    cpu: 3175m\n    memory: 6127Mi\n    nvidia.com/gpu: 0\n\n- seconds: 5\n  resourceUsage:\n    cpu: 3277m\n    memory: 6160Mi\n    nvidia.com/gpu: 0\n\n- seconds: 5\n  resourceUsage:\n    cpu: 3089m\n    memory: 6135Mi\n    nvidia.com/gpu: 0\n\n- seconds: 5\n  resourceUsage:\n    cpu: 3300m\n    memory: 6176Mi\n    nvidia.com/gpu: 0\n\n- seconds: 5\n  resourceUsage:\n    cpu: 3070m\n    memory: 6127Mi\n    nvidia.com/gpu: 0\n\n- seconds: 5\n  resourceUsage:\n    cpu: 3203m\n    memory: 6160Mi\n    nvidia.com/gpu: 0\n\n- seconds: 5\n  resourceUsage:\n    cpu: 3043m\n    memory: 6135Mi\n    nvidia.com/gpu: 0\n\n- seconds: 5\n  resourceUsage:\n    cpu: 3257m\n    memory: 6168Mi\n    nvidia.com/gpu: 0\n\n- seconds: 5\n  resourceUsage:\n    cpu: 3121m\n    memory: 6119Mi\n    nvidia.com/gpu: 0\n\n- seconds: 5\n  resourceUsage:\n    cpu: 3292m\n    memory: 6183Mi\n    nvidia.com/gpu: 0\n\n- seconds: 5\n  resourceUsage:\n    cpu: 3093m\n    memory: 6127Mi\n    nvidia.com/gpu: 0\n\n- seconds: 5\n  resourceUsage:\n    cpu: 3273m\n    memory: 6160Mi\n    nvidia.com/gpu: 0\n\n- seconds: 5\n  resourceUsage:\n    cpu: 3117m\n    memory: 6119Mi\n    nvidia.com/gpu: 0\n\n- seconds: 5\n  resourceUsage:\n    cpu: 3234m\n    memory: 6160Mi\n    nvidia.com/gpu: 0\n\n- seconds: 5\n  resourceUsage:\n    cpu: 3082m\n    memory: 6119Mi\n    nvidia.com/gpu: 0\n\n- seconds: 5\n  resourceUsage:\n    cpu: 3281m\n    memory: 6168Mi\n    nvidia.com/gpu: 0\n\n- seconds: 5\n  resourceUsage:\n    cpu: 3093m\n    memory: 6111Mi\n    nvidia.com/gpu: 0\n\n- seconds: 5\n  resourceUsage:\n    cpu: 3344m\n    memory: 6160Mi\n    nvidia.com/gpu: 0\n\n- seconds: 5\n  resourceUsage:\n    cpu: 3246m\n    memory: 6127Mi\n    nvidia.com/gpu: 0\n\n- seconds: 5\n  resourceUsage:\n    cpu: 3246m\n    memory: 6191Mi\n    nvidia.com/gpu: 0\n\n- seconds: 5\n  resourceUsage:\n    cpu: 3644m\n    memory: 6127Mi\n    nvidia.com/gpu: 0\n\n- seconds: 5\n  resourceUsage:\n    cpu: 2913m\n    memory: 6152Mi\n    nvidia.com/gpu: 0\n\n- seconds: 5\n  resourceUsage:\n    cpu: 3585m\n    memory: 6168Mi\n    nvidia.com/gpu: 0\n\n- seconds: 5\n  resourceUsage:\n    cpu: 3043m\n    memory: 6160Mi\n    nvidia.com/gpu: 0\n\n- seconds: 5\n  resourceUsage:\n    cpu: 3367m\n    memory: 6152Mi\n    nvidia.com/gpu: 0\n\n- seconds: 5\n  resourceUsage:\n    cpu: 3078m\n    memory: 6127Mi\n    nvidia.com/gpu: 0\n\n- seconds: 5\n  resourceUsage:\n    cpu: 3402m\n    memory: 6183Mi\n    nvidia.com/gpu: 0\n\n- seconds: 5\n  resourceUsage:\n    cpu: 3125m\n    memory: 6135Mi\n    nvidia.com/gpu: 0\n\n- seconds: 5\n  resourceUsage:\n    cpu: 3370m\n    memory: 6160Mi\n    nvidia.com/gpu: 0\n\n- seconds: 5\n  resourceUsage:\n    cpu: 3136m\n    memory: 6127Mi\n    nvidia.com/gpu: 0\n\n- seconds: 5\n  resourceUsage:\n    cpu: 3550m\n    memory: 6191Mi\n    nvidia.com/gpu: 0\n\n- seconds: 5\n  resourceUsage:\n    cpu: 3277m\n    memory: 6144Mi\n    nvidia.com/gpu: 0\n\n- seconds: 5\n  resourceUsage:\n    cpu: 3312m\n    memory: 6168Mi\n    nvidia.com/gpu: 0\n\n- seconds: 5\n  resourceUsage:\n    cpu: 3894m\n    memory: 6152Mi\n    nvidia.com/gpu: 0\n\n- seconds: 5\n  resourceUsage:\n    cpu: 3089m\n    memory: 6176Mi\n    nvidia.com/gpu: 0\n\n- seconds: 5\n  resourceUsage:\n    cpu: 3722m\n    memory: 6191Mi\n    nvidia.com/gpu: 0\n\n- seconds: 5\n  resourceUsage:\n    cpu: 3230m\n    memory: 6152Mi\n    nvidia.com/gpu: 0\n\n- seconds: 5\n  resourceUsage:\n    cpu: 3617m\n    memory: 6207Mi\n    nvidia.com/gpu: 0\n\n- seconds: 5\n  resourceUsage:\n    cpu: 3257m\n    memory: 6160Mi\n    nvidia.com/gpu: 0\n\n- seconds: 5\n  resourceUsage:\n    cpu: 3570m\n    memory: 6183Mi\n    nvidia.com/gpu: 0\n\n- seconds: 5\n  resourceUsage:\n    cpu: 3257m\n    memory: 6135Mi\n    nvidia.com/gpu: 0\n\n- seconds: 5\n  resourceUsage:\n    cpu: 3546m\n    memory: 6191Mi\n    nvidia.com/gpu: 0\n\n- seconds: 5\n  resourceUsage:\n    cpu: 3816m\n    memory: 6176Mi\n    nvidia.com/gpu: 0\n\n- seconds: 5\n  resourceUsage:\n    cpu: 3261m\n    memory: 6168Mi\n    nvidia.com/gpu: 0\n\n- seconds: 5\n  resourceUsage:\n    cpu: 3648m\n    memory: 6183Mi\n    nvidia.com/gpu: 0\n\n- seconds: 5\n  resourceUsage:\n    cpu: 3445m\n    memory: 6168Mi\n    nvidia.com/gpu: 0\n\n- seconds: 5\n  resourceUsage:\n    cpu: 3574m\n    memory: 6199Mi\n    nvidia.com/gpu: 0\n\n- seconds: 5\n  resourceUsage:\n    cpu: 3464m\n    memory: 6176Mi\n    nvidia.com/gpu: 0\n\n- seconds: 5\n  resourceUsage:\n    cpu: 3550m\n    memory: 6215Mi\n    nvidia.com/gpu: 0\n\n- seconds: 5\n  resourceUsage:\n    cpu: 3500m\n    memory: 6152Mi\n    nvidia.com/gpu: 0\n\n- seconds: 5\n  resourceUsage:\n    cpu: 3418m\n    memory: 6199Mi\n    nvidia.com/gpu: 0\n\n- seconds: 5\n  resourceUsage:\n    cpu: 3964m\n    memory: 6191Mi\n    nvidia.com/gpu: 0\n\n- seconds: 5\n  resourceUsage:\n    cpu: 3285m\n    memory: 6176Mi\n    nvidia.com/gpu: 0\n\n- seconds: 5\n  resourceUsage:\n    cpu: 3585m\n    memory: 6191Mi\n    nvidia.com/gpu: 0\n\n- seconds: 5\n  resourceUsage:\n    cpu: 3242m\n    memory: 6152Mi\n    nvidia.com/gpu: 0\n\n- seconds: 5\n  resourceUsage:\n    cpu: 3582m\n    memory: 6207Mi\n    nvidia.com/gpu: 0\n\n- seconds: 5\n  resourceUsage:\n    cpu: 3300m\n    memory: 6160Mi\n    nvidia.com/gpu: 0\n\n- seconds: 5\n  resourceUsage:\n    cpu: 3539m\n    memory: 6191Mi\n    nvidia.com/gpu: 0\n\n- seconds: 5\n  resourceUsage:\n    cpu: 3890m\n    memory: 6191Mi\n    nvidia.com/gpu: 0\n\n- seconds: 5\n  resourceUsage:\n    cpu: 3383m\n    memory: 6183Mi\n    nvidia.com/gpu: 0\n\n- seconds: 5\n  resourceUsage:\n    cpu: 3441m\n    memory: 6199Mi\n    nvidia.com/gpu: 0\n\n- seconds: 5\n  resourceUsage:\n    cpu: 3374m\n    memory: 6160Mi\n    nvidia.com/gpu: 0\n\n- seconds: 5\n  resourceUsage:\n    cpu: 3402m\n    memory: 6207Mi\n    nvidia.com/gpu: 0\n\n- seconds: 5\n  resourceUsage:\n    cpu: 3340m\n    memory: 6176Mi\n    nvidia.com/gpu: 0\n\n- seconds: 5\n  resourceUsage:\n    cpu: 3457m\n    memory: 6191Mi\n    nvidia.com/gpu: 0\n\n- seconds: 5\n  resourceUsage:\n    cpu: 3921m\n    memory: 6191Mi\n    nvidia.com/gpu: 0\n\n- seconds: 5\n  resourceUsage:\n    cpu: 3027m\n    memory: 6191Mi\n    nvidia.com/gpu: 0\n\n- seconds: 5\n  resourceUsage:\n    cpu: 3660m\n    memory: 6207Mi\n    nvidia.com/gpu: 0\n\n- seconds: 5\n  resourceUsage:\n    cpu: 3168m\n    memory: 6183Mi\n    nvidia.com/gpu: 0\n\n- seconds: 5\n  resourceUsage:\n    cpu: 3441m\n    memory: 6224Mi\n    nvidia.com/gpu: 0\n\n- seconds: 5\n  resourceUsage:\n    cpu: 3164m\n    memory: 6168Mi\n    nvidia.com/gpu: 0\n\n- seconds: 5\n  resourceUsage:\n    cpu: 3613m\n    memory: 6224Mi\n    nvidia.com/gpu: 0\n\n- seconds: 5\n  resourceUsage:\n    cpu: 3836m\n    memory: 6199Mi\n    nvidia.com/gpu: 0\n\n- seconds: 5\n  resourceUsage:\n    cpu: 3000m\n    memory: 6191Mi\n    nvidia.com/gpu: 0\n\n- seconds: 5\n  resourceUsage:\n    cpu: 3636m\n    memory: 6207Mi\n    nvidia.com/gpu: 0\n\n- seconds: 5\n  resourceUsage:\n    cpu: 3304m\n    memory: 6191Mi\n    nvidia.com/gpu: 0\n\n- seconds: 5\n  resourceUsage:\n    cpu: 3370m\n    memory: 6232Mi\n    nvidia.com/gpu: 0\n\n- seconds: 5\n  resourceUsage:\n    cpu: 3281m\n    memory: 6176Mi\n    nvidia.com/gpu: 0\n\n- seconds: 5\n  resourceUsage:\n    cpu: 3379m\n    memory: 6199Mi\n    nvidia.com/gpu: 0\n\n- seconds: 5\n  resourceUsage:\n    cpu: 3765m\n    memory: 6183Mi\n    nvidia.com/gpu: 0\n\n- seconds: 5\n  resourceUsage:\n    cpu: 2874m\n    memory: 6207Mi\n    nvidia.com/gpu: 0\n\n- seconds: 5\n  resourceUsage:\n    cpu: 3832m\n    memory: 6199Mi\n    nvidia.com/gpu: 0\n\n- seconds: 5\n  resourceUsage:\n    cpu: 3148m\n    memory: 6191Mi\n    nvidia.com/gpu: 0\n\n- seconds: 5\n  resourceUsage:\n    cpu: 3413m\n    memory: 6232Mi\n    nvidia.com/gpu: 0\n\n- seconds: 5\n  resourceUsage:\n    cpu: 3128m\n    memory: 6168Mi\n    nvidia.com/gpu: 0\n\n- seconds: 5\n  resourceUsage:\n    cpu: 3535m\n    memory: 6215Mi\n    nvidia.com/gpu: 0\n\n- seconds: 5\n  resourceUsage:\n    cpu: 3769m\n    memory: 6199Mi\n    nvidia.com/gpu: 0\n\n- seconds: 5\n  resourceUsage:\n    cpu: 2972m\n    memory: 6232Mi\n    nvidia.com/gpu: 0\n\n- seconds: 5\n  resourceUsage:\n    cpu: 3683m\n    memory: 6232Mi\n    nvidia.com/gpu: 0\n\n- seconds: 5\n  resourceUsage:\n    cpu: 3304m\n    memory: 6199Mi\n    nvidia.com/gpu: 0\n\n- seconds: 5\n  resourceUsage:\n    cpu: 3367m\n    memory: 6240Mi\n    nvidia.com/gpu: 0\n\n- seconds: 5\n  resourceUsage:\n    cpu: 3253m\n    memory: 6183Mi\n    nvidia.com/gpu: 0\n\n- seconds: 5\n  resourceUsage:\n    cpu: 3316m\n    memory: 6232Mi\n    nvidia.com/gpu: 0\n\n- seconds: 5\n  resourceUsage:\n    cpu: 3843m\n    memory: 6215Mi\n    nvidia.com/gpu: 0\n\n- seconds: 5\n  resourceUsage:\n    cpu: 2952m\n    memory: 6224Mi\n    nvidia.com/gpu: 0\n\n- seconds: 5\n  resourceUsage:\n    cpu: 3632m\n    memory: 6240Mi\n    nvidia.com/gpu: 0\n\n- seconds: 5\n  resourceUsage:\n    cpu: 3238m\n    memory: 6191Mi\n    nvidia.com/gpu: 0\n\n- seconds: 5\n  resourceUsage:\n    cpu: 3496m\n    memory: 6248Mi\n    nvidia.com/gpu: 0\n\n- seconds: 5\n  resourceUsage:\n    cpu: 2995m\n    memory: 6199Mi\n    nvidia.com/gpu: 0\n\n- seconds: 5\n  resourceUsage:\n    cpu: 3710m\n    memory: 6248Mi\n    nvidia.com/gpu: 0\n\n- seconds: 5\n  resourceUsage:\n    cpu: 3843m\n    memory: 6224Mi\n    nvidia.com/gpu: 0\n\n- seconds: 5\n  resourceUsage:\n    cpu: 3097m\n    memory: 6215Mi\n    nvidia.com/gpu: 0\n\n- seconds: 5\n  resourceUsage:\n    cpu: 3511m\n    memory: 6215Mi\n    nvidia.com/gpu: 0\n\n- seconds: 5\n  resourceUsage:\n    cpu: 3207m\n    memory: 6191Mi\n    nvidia.com/gpu: 0\n\n- seconds: 5\n  resourceUsage:\n    cpu: 3265m\n    memory: 6240Mi\n    nvidia.com/gpu: 0\n\n- seconds: 5\n  resourceUsage:\n    cpu: 3175m\n    memory: 6183Mi\n    nvidia.com/gpu: 0\n\n- seconds: 5\n  resourceUsage:\n    cpu: 3207m\n    memory: 6224Mi\n    nvidia.com/gpu: 0\n\n- seconds: 5\n  resourceUsage:\n    cpu: 3312m\n    memory: 6191Mi\n    nvidia.com/gpu: 0\n\n- seconds: 5\n  resourceUsage:\n    cpu: 3034m\n    memory: 6248Mi\n    nvidia.com/gpu: 0\n\n- seconds: 5\n  resourceUsage:\n    cpu: 3664m\n    memory: 6199Mi\n    nvidia.com/gpu: 0\n\n- seconds: 5\n  resourceUsage:\n    cpu: 2636m\n    memory: 6232Mi\n    nvidia.com/gpu: 0\n\n- seconds: 5\n  resourceUsage:\n    cpu: 3640m\n    memory: 6224Mi\n    nvidia.com/gpu: 0\n\n- seconds: 5\n  resourceUsage:\n    cpu: 2570m\n    memory: 6207Mi\n    nvidia.com/gpu: 0\n"
		}
	},
	"spec": {
		"containers": [
			{
				"name": "container",
				"image": "container",
				"resources": {
					"limits": {
						"cpu": "999",
						"memory": "999Gi",
						"nvidia.com/gpu": "0"
					},
					"requests": {
						"cpu": "4",
						"memory": "8336Mi",
						"nvidia.com/gpu": "0"
					}
				}
			}
		],
		"priority": 1
	},
	"status": {}
}
